[
    {
        "stories": [
            {
                "story_id": 5,
                "sort_num": 5,
                "chinese_title": "丛林探险",
                "english_title": "Jungle Adventure",
                "description": "This is a relatively long description",
                "big_image_url": "/media/cat1/s1/big.jpg",
                "small_image_url": "/media/cat1/s1/small.jpg",
                "duration": 10
            },
            {
                "story_id": 6,
                "sort_num": 6,
                "chinese_title": "海底世界",
                "english_title": "Underwater World",
                "description": "This is a relatively long description",
                "big_image_url": "/media/cat1/s2/big.jpg",
                "small_image_url": "/media/cat1/s2/small.jpg",
                "duration": 384
            },
            {
                "story_id": 7,
                "sort_num": 7,
                "chinese_title": "小王子",
                "english_title": "Little Prince",
                "description": "This is a relatively long description",
                "big_image_url": "/media/cat1/s3/big.jpg",
                "small_image_url": "/media/cat1/s3/small.jpg",
                "duration": 304
            },
            {
                "story_id": 8,
                "sort_num": 8,
                "chinese_title": "魔幻城堡",
                "english_title": "Magic Castle",
                "description": "This is a relatively long description",
                "big_image_url": "/media/cat1/s4/big.jpg",
                "small_image_url": "/media/cat1/s4/small.jpg",
                "duration": 324
            },
            {
                "story_id": 9,
                "sort_num": 9,
                "chinese_title": "公主日记",
                "english_title": "Princess Diary",
                "description": "This is a relatively long description",
                "big_image_url": "/media/cat1/s5/big.jpg",
                "small_image_url": "/media/cat1/s5/small.jpg",
                "duration": 291
            },
            {
                "story_id": 10,
                "sort_num": 10,
                "chinese_title": "维尼熊",
                "english_title": "Pooh Bear",
                "description": "This is a relatively long description",
                "big_image_url": "/media/cat1/s6/big.jpg",
                "small_image_url": "/media/cat1/s6/small.jpg",
                "duration": 298
            },
            {
                "story_id": 11,
                "sort_num": 11,
                "chinese_title": "超级英雄",
                "english_title": "Super Hero",
                "description": "This is a relatively long description",
                "big_image_url": "/media/cat1/s7/big.jpg",
                "small_image_url": "/media/cat1/s7/small.jpg",
                "duration": 306
            },
            {
                "story_id": 12,
                "sort_num": 12,
                "chinese_title": "超人归来",
                "english_title": "Superman Returns",
                "description": "This is a relatively long description",
                "big_image_url": "/media/cat1/s8/big.jpg",
                "small_image_url": "/media/cat1/s8/small.jpg",
                "duration": 321
            },
            {
                "story_id": 109,
                "sort_num": 109,
                "chinese_title": "银河旅行",
                "english_title": "Galaxy Travel",
                "description": "This is a relatively long description",
                "big_image_url": "/media/cat1/s9/big.jpg",
                "small_image_url": "/media/cat1/s9/small.jpg",
                "duration": 273
            },
            {
                "story_id": 110,
                "sort_num": 110,
                "chinese_title": "地球日记",
                "english_title": "Earth Diary",
                "big_image_url": "/media/cat1/s10/big.jpg",
                "small_image_url": "/media/cat1/s10/small.jpg",
                "description": "This is a relatively long description",
                "duration": 460
            },
            {
                "story_id": 111,
                "sort_num": 15,
                "chinese_title": "光环",
                "english_title": "Halo",
                "big_image_url": "/media/cat1/s11/big.jpg",
                "small_image_url": "/media/cat1/s11/small.jpg",
                "description": "This is a relatively long description",
                "duration": 486
            }
        ],
        "album_id": 1,
        "sort_num": 1,
        "chinese_name": "童话派对",
        "english_name": "Fairy tale Theme party",
        "big_image_url": "/media/cat1/big.jpg",
        "small_image_url": "/media/cat1/small.jpg",
        "description": "This is a relatively long description"
    },
    {
        "stories": [
            {
                "story_id": 1,
                "sort_num": 1,
                "chinese_title": "梵高宇宙",
                "english_title": "Van Gogh universe",
                "description": "This is a relatively long description",
                "big_image_url": "/media/cat2/s1/big.jpg",
                "small_image_url": "/media/cat2/s1/small.jpg",
                "duration": 480
            },
            {
                "story_id": 2,
                "sort_num": 2,
                "chinese_title": "星空探索",
                "english_title": "Star Quest",
                "description": "This is a relatively long description",
                "big_image_url": "/media/cat2/s2/big.jpg",
                "small_image_url": "/media/cat2/s2/small.jpg",
                "duration": 278
            },
            {
                "story_id": 3,
                "sort_num": 3,
                "chinese_title": "未来",
                "english_title": "Future",
                "big_image_url": "/media/cat2/s3/big.jpg",
                "small_image_url": "/media/cat2/s3/small.jpg",
                "description": "This is a relatively long description",
                "duration": 480
            },
            {
                "story_id": 4,
                "sort_num": 4,
                "chinese_title": "虚幻美景",
                "english_title": "Unreal Beauty",
                "big_image_url": "/media/cat2/s4/big.jpg",
                "small_image_url": "/media/cat2/s4/small.jpg",
                "description": "This is a relatively long description",
                "duration": 485
            },
            {
                "story_id": 13,
                "sort_num": 13,
                "chinese_title": "银河旅行",
                "english_title": "Galaxy Travel",
                "description": "This is a relatively long description",
                "big_image_url": "/media/cat2/s5/big.jpg",
                "small_image_url": "/media/cat2/s5/small.jpg",
                "duration": 278
            },
            {
                "story_id": 14,
                "sort_num": 14,
                "chinese_title": "地球日记",
                "english_title": "Earth Diary",
                "big_image_url": "/media/cat2/s6/big.jpg",
                "small_image_url": "/media/cat2/s6/small.jpg",
                "description": "This is a relatively long description",
                "duration": 460
            },
            {
                "story_id": 15,
                "sort_num": 15,
                "chinese_title": "光环",
                "english_title": "Halo",
                "big_image_url": "/media/cat2/s7/big.jpg",
                "small_image_url": "/media/cat2/s7/small.jpg",
                "description": "This is a relatively long description",
                "duration": 480
            }
        ],
        "album_id": 2,
        "sort_num": 2,
        "chinese_name": "虚拟主题",
        "english_name": "Unreal Theme",
        "big_image_url": "/media/cat2/big.jpg",
        "small_image_url": "/media/cat2/small.jpg",
        "description": "This is a relatively long description"
    },
    {
        "stories": [
            {
                "story_id": 16,
                "sort_num": 16,
                "chinese_title": "丛林探险",
                "english_title": "Jungle Adventure",
                "description": "This is a relatively long description",
                "big_image_url": "/media/cat3/s1/big.jpg",
                "small_image_url": "/media/cat3/s1/small.jpg",
                "duration": 670
            },
            {
                "story_id": 17,
                "sort_num": 17,
                "chinese_title": "海底世界",
                "english_title": "Underwater World",
                "description": "This is a relatively long description",
                "big_image_url": "/media/cat3/s2/big.jpg",
                "small_image_url": "/media/cat3/s2/small.jpg",
                "duration": 384
            },
            {
                "story_id": 18,
                "sort_num": 18,
                "chinese_title": "小王子",
                "english_title": "Little Prince",
                "description": "This is a relatively long description",
                "big_image_url": "/media/cat3/s3/big.jpg",
                "small_image_url": "/media/cat3/s3/small.jpg",
                "duration": 304
            },
            {
                "story_id": 19,
                "sort_num": 19,
                "chinese_title": "魔幻城堡",
                "english_title": "Magic Castle",
                "description": "This is a relatively long description",
                "big_image_url": "/media/cat3/s4/big.jpg",
                "small_image_url": "/media/cat3/s4/small.jpg",
                "duration": 324
            },
            {
                "story_id": 20,
                "sort_num": 20,
                "chinese_title": "公主日记",
                "english_title": "Princess Diary",
                "description": "This is a relatively long description",
                "big_image_url": "/media/cat3/s5/big.jpg",
                "small_image_url": "/media/cat3/s5/small.jpg",
                "duration": 291
            },
            {
                "story_id": 21,
                "sort_num": 21,
                "chinese_title": "维尼熊",
                "english_title": "Pooh Bear",
                "description": "This is a relatively long description",
                "big_image_url": "/media/cat3/s6/big.jpg",
                "small_image_url": "/media/cat3/s6/small.jpg",
                "duration": 298
            },
            {
                "story_id": 22,
                "sort_num": 22,
                "chinese_title": "超级英雄",
                "english_title": "Super Hero",
                "description": "This is a relatively long description",
                "big_image_url": "/media/cat3/s7/big.jpg",
                "small_image_url": "/media/cat3/s7/small.jpg",
                "duration": 306
            },
            {
                "story_id": 23,
                "sort_num": 23,
                "chinese_title": "超人归来",
                "english_title": "Superman Returns",
                "description": "This is a relatively long description",
                "big_image_url": "/media/cat3/s8/big.jpg",
                "small_image_url": "/media/cat3/s8/small.jpg",
                "duration": 321
            }
        ],
        "album_id": 3,
        "sort_num": 3,
        "chinese_name": "光之旅",
        "english_name": "The Light Journey",
        "big_image_url": "/media/cat3/big.jpg",
        "small_image_url": "/media/cat3/small.jpg",
        "description": "This is a relatively long description"
    },
    {
        "stories": [
            {
                "story_id": 41,
                "sort_num": 41,
                "chinese_title": "丛林探险",
                "english_title": "Jungle Adventure",
                "description": "This is a relatively long description",
                "big_image_url": "/media/cat4/s1/big.jpg",
                "small_image_url": "/media/cat4/s1/small.jpg",
                "duration": 670
            },
            {
                "story_id": 42,
                "sort_num": 42,
                "chinese_title": "海底世界",
                "english_title": "Underwater World",
                "description": "This is a relatively long description",
                "big_image_url": "/media/cat4/s2/big.jpg",
                "small_image_url": "/media/cat4/s2/small.jpg",
                "duration": 384
            },
            {
                "story_id": 43,
                "sort_num": 43,
                "chinese_title": "小王子",
                "english_title": "Little Prince",
                "description": "This is a relatively long description",
                "big_image_url": "/media/cat4/s3/big.jpg",
                "small_image_url": "/media/cat4/s3/small.jpg",
                "duration": 304
            },
            {
                "story_id": 44,
                "sort_num": 44,
                "chinese_title": "魔幻城堡",
                "english_title": "Magic Castle",
                "description": "This is a relatively long description",
                "big_image_url": "/media/cat4/s4/big.jpg",
                "small_image_url": "/media/cat4/s4/small.jpg",
                "duration": 324
            },
            {
                "story_id": 45,
                "sort_num": 45,
                "chinese_title": "公主日记",
                "english_title": "Princess Diary",
                "description": "This is a relatively long description",
                "big_image_url": "/media/cat4/s5/big.jpg",
                "small_image_url": "/media/cat4/s5/small.jpg",
                "duration": 291
            },
            {
                "story_id": 46,
                "sort_num": 46,
                "chinese_title": "维尼熊",
                "english_title": "Pooh Bear",
                "description": "This is a relatively long description",
                "big_image_url": "/media/cat4/s6/big.jpg",
                "small_image_url": "/media/cat4/s6/small.jpg",
                "duration": 298
            },
            {
                "story_id": 47,
                "sort_num": 47,
                "chinese_title": "超级英雄",
                "english_title": "Super Hero",
                "description": "This is a relatively long description",
                "big_image_url": "/media/cat4/s7/big.jpg",
                "small_image_url": "/media/cat4/s7/small.jpg",
                "duration": 306
            },
            {
                "story_id": 48,
                "sort_num": 47,
                "chinese_title": "超人归来",
                "english_title": "Superman Returns",
                "description": "This is a relatively long description",
                "big_image_url": "/media/cat4/s8/big.jpg",
                "small_image_url": "/media/cat4/s8/small.jpg",
                "duration": 321
            }
        ],
        "album_id": 4,
        "sort_num": 4,
        "chinese_name": "宇宙旅行",
        "english_name": "Space travel",
        "big_image_url": "/media/cat4/big.jpg",
        "small_image_url": "/media/cat4/small.jpg",
        "description": "This is a relatively long description"
    },
    {
        "stories": [
            {
                "story_id": 51,
                "sort_num": 51,
                "chinese_title": "丛林探险",
                "english_title": "Jungle Adventure",
                "description": "This is a relatively long description",
                "big_image_url": "/media/cat5/s1/big.jpg",
                "small_image_url": "/media/cat5/s1/small.jpg",
                "duration": 670
            },
            {
                "story_id": 52,
                "sort_num": 52,
                "chinese_title": "海底世界",
                "english_title": "Underwater World",
                "description": "This is a relatively long description",
                "big_image_url": "/media/cat5/s2/big.jpg",
                "small_image_url": "/media/cat5/s2/small.jpg",
                "duration": 384
            },
            {
                "story_id": 53,
                "sort_num": 53,
                "chinese_title": "小王子",
                "english_title": "Little Prince",
                "description": "This is a relatively long description",
                "big_image_url": "/media/cat5/s3/big.jpg",
                "small_image_url": "/media/cat5/s3/small.jpg",
                "duration": 304
            },
            {
                "story_id": 54,
                "sort_num": 54,
                "chinese_title": "魔幻城堡",
                "english_title": "Magic Castle",
                "description": "This is a relatively long description",
                "big_image_url": "/media/cat5/s4/big.jpg",
                "small_image_url": "/media/cat5/s4/small.jpg",
                "duration": 324
            },
            {
                "story_id": 55,
                "sort_num": 55,
                "chinese_title": "公主日记",
                "english_title": "Princess Diary",
                "description": "This is a relatively long description",
                "big_image_url": "/media/cat5/s5/big.jpg",
                "small_image_url": "/media/cat5/s5/small.jpg",
                "duration": 291
            },
            {
                "story_id": 56,
                "sort_num": 56,
                "chinese_title": "维尼熊",
                "english_title": "Pooh Bear",
                "description": "This is a relatively long description",
                "big_image_url": "/media/cat5/s6/big.jpg",
                "small_image_url": "/media/cat5/s6/small.jpg",
                "duration": 298
            },
            {
                "story_id": 57,
                "sort_num": 57,
                "chinese_title": "超级英雄",
                "english_title": "Super Hero",
                "description": "This is a relatively long description",
                "big_image_url": "/media/cat5/s7/big.jpg",
                "small_image_url": "/media/cat5/s7/small.jpg",
                "duration": 306
            },
            {
                "story_id": 58,
                "sort_num": 58,
                "chinese_title": "超人归来",
                "english_title": "Superman Returns",
                "description": "This is a relatively long description",
                "big_image_url": "/media/cat5/s8/big.jpg",
                "small_image_url": "/media/cat5/s8/small.jpg",
                "duration": 321
            }
        ],
        "album_id": 5,
        "sort_num": 5,
        "chinese_name": "夜游",
        "english_name": "Night",
        "big_image_url": "/media/cat5/big.jpg",
        "small_image_url": "/media/cat5/small.jpg",
        "description": "This is a relatively long description"
    }

]
